{
    "title": "Mutton Vindaloo",
    "image": "muttonVindaloo.jpeg",
    "ingredients": [
        {"name": "0", "quantity": "500g"},
        {"name": "1", "quantity": "200g"},
        {"name": "2", "quantity": "1 tbsp"},
        {"name": "3", "quantity": "1 tsp"},
        {"name": "4", "quantity": "2 tbsp"},
        {"name": "5", "quantity": "2 tbsp"},
        {"name": "7", "quantity": "4 tbsp"},
        {"name": "9", "quantity": "1/2 cup"},
        {"name": "6", "quantity": "4 tbsp"},
        {"name": "35", "quantity": "1/4 cup"},
        {"name": "36", "quantity": "4 cloves garlic"},
        {"name": "30", "quantity": "2 tomatoes (chopped)"},
        {"name": "13", "quantity": "for garnish"},
        {"name": "16", "quantity": "1 tsp"},
        {"name": "19", "quantity": "1 tsp"}
    ],
    "procedure": [
        "Marinate lamb in vinegar, turmeric, and red chili powder for 1 hour.",
        "Heat oil in a pan, add onions and sauté till golden brown.",
        "Add ginger garlic paste and chopped garlic, cooking till fragrant.",
        "Add marinated lamb and sauté on high heat.",
        "Add chopped tomatoes and cook till they soften.",
        "Pour in milk and cook till the gravy thickens.",
        "Garnish with coriander and serve with steamed rice."
    ]
}
